CHANGELOG.md
MANIFEST.in
README.md
requirements.txt
setup.py
keras_bert/__init__.py
keras_bert/backend.py
keras_bert/bert.py
keras_bert/loader.py
keras_bert/tokenizer.py
keras_bert/util.py
keras_bert.egg-info/PKG-INFO
keras_bert.egg-info/SOURCES.txt
keras_bert.egg-info/dependency_links.txt
keras_bert.egg-info/requires.txt
keras_bert.egg-info/top_level.txt
keras_bert/datasets/__init__.py
keras_bert/datasets/pretrained.py
keras_bert/layers/__init__.py
keras_bert/layers/conv.py
keras_bert/layers/embedding.py
keras_bert/layers/extract.py
keras_bert/layers/inputs.py
keras_bert/layers/masked.py
keras_bert/layers/pooling.py
keras_bert/layers/task_embed.py
keras_bert/optimizers/__init__.py
keras_bert/optimizers/util.py
keras_bert/optimizers/warmup_v2.py
tests/__init__.py
tests/test_bert.py
tests/test_loader.py
tests/test_tokenizer.py
tests/test_util.py
tests/datasets/__init__.py
tests/datasets/test_get_pretrained.py
tests/layers/__init__.py
tests/layers/test_conv.py
tests/layers/test_embedding.py
tests/layers/test_extract.py
tests/layers/test_inputs.py
tests/layers/test_masked.py
tests/layers/test_pooling.py
tests/layers/test_task_embed.py
tests/optimizers/__init__.py
tests/optimizers/test_warmup.py