Metadata-Version: 2.1
Name: keras-bert
Version: 0.86.0
Summary: BERT implemented in Keras
Home-page: https://github.com/CyberZHG/keras-bert
Author: CyberZHG
Author-email: CyberZHG@users.noreply.github.com
License: MIT
Platform: UNKNOWN
Classifier: Programming Language :: Python :: 3
Classifier: License :: OSI Approved :: MIT License
Classifier: Operating System :: OS Independent
